AUTHORS.rst
CONTRIBUTING.rst
HISTORY.rst
LICENSE
MANIFEST.in
README.rst
setup.cfg
setup.py
ca_util/__init__.py
ca_util/domain_model.py
ca_util/request_object.py
ca_util/response_object.py
ca_util/use_case.py
ca_util.egg-info/PKG-INFO
ca_util.egg-info/SOURCES.txt
ca_util.egg-info/dependency_links.txt
ca_util.egg-info/not-zip-safe
ca_util.egg-info/requires.txt
ca_util.egg-info/top_level.txt
docs/Makefile
docs/authors.rst
docs/conf.py
docs/contributing.rst
docs/history.rst
docs/index.rst
docs/installation.rst
docs/make.bat
docs/readme.rst
docs/usage.rst
tests/__init__.py