Metadata-Version: 1.2
Name: ca-util
Version: 0.1.0
Summary: Utility class for building Python projects based on clean architecture.
Home-page: https://github.com/yoophi/ca-util
Author: Pyunghyuk Yoo
Author-email: yoophi@gmail.com
License: MIT license
Keywords: ca-util
Platform: UNKNOWN
Classifier: Development Status :: 2 - Pre-Alpha
Classifier: Intended Audience :: Developers
Classifier: License :: OSI Approved :: MIT License
Classifier: Natural Language :: English
Classifier: Programming Language :: Python :: 3
Classifier: Programming Language :: Python :: 3.5
Classifier: Programming Language :: Python :: 3.6
Classifier: Programming Language :: Python :: 3.7
Classifier: Programming Language :: Python :: 3.8
Requires-Python: >=3.5
